device_fingerprint/__init__.py
device_fingerprint/fingerprint.py
Device_Fingerprint-1.0.dist-info/METADATA
Device_Fingerprint-1.0.dist-info/WHEEL
Device_Fingerprint-1.0.dist-info/top_level.txt
Device_Fingerprint-1.0.dist-info/RECORD
