Metadata-Version: 2.1
Name: Device-Fingerprint
Version: 1.0
Summary: Python library to generate a unique device fingerprint based on physical characteristics
Home-page: https://github.com/saiadupa/Device-fingerprints
Author: Adupa Nithin Sai
Author-email: adupanithinsai@example.com
Classifier: Programming Language :: Python :: 3
Classifier: Operating System :: OS Independent
